{"animations":[{"anim":"singLEFT","fps":24,"indices":[],"loop":false,"name":"gffisk left","offsets":[0,0]},{"anim":"singDOWN","fps":24,"indices":[],"loop":false,"name":"gffisk down","offsets":[0,0]},{"anim":"singUP","fps":24,"indices":[],"loop":false,"name":"gffisk up","offsets":[0,0]},{"anim":"singRIGHT","fps":24,"indices":[],"loop":false,"name":"gffisk right","offsets":[0,0]},{"anim":"idle","fps":24,"indices":[],"loop":false,"name":"gffisk idle","offsets":[0,0]},{"anim":"god","fps":24,"indices":[],"loop":false,"name":"the power of God","offsets":[0,0]}],"camera_position":[200,-100],"flip_x":true,"healthbar_colors":[102,57,49],"healthicon":"gfFisk","image":"characters/gffisk_assets","no_antialiasing":true,"position":[850,335],"scale":3,"sing_duration":3.00000000000001}